{
  "project_info": {
    "project_number": "376365295838",
    "firebase_url": "https://mechili-462b9.firebaseio.com",
    "project_id": "mechili-462b9",
    "storage_bucket": "mechili-462b9.appspot.com"
  },
  "client": [
    {
      "client_info": {
        "mobilesdk_app_id": "1:376365295838:android:f7c3451bfa8855a1cffa4f",
        "android_client_info": {
          "package_name": "com.example.mechily"
        }
      },
      "oauth_client": [
        {
          "client_id": "376365295838-vqhh7jda709qqfc41peem57dkvedvuhd.apps.googleusercontent.com",
          "client_type": 3
        }
      ],
      "api_key": [
        {
          "current_key": "AIzaSyCC-N8vJ1vHLs_hMRDasG0nD9SHIIlhDFk"
        }
      ],
      "services": {
        "appinvite_service": {
          "other_platform_oauth_client": [
            {
              "client_id": "376365295838-vqhh7jda709qqfc41peem57dkvedvuhd.apps.googleusercontent.com",
              "client_type": 3
            },
            {
              "client_id": "376365295838-6svdrgdonll430r5plsjpmjmtre5ohrs.apps.googleusercontent.com",
              "client_type": 2,
              "ios_info": {
                "bundle_id": "com.example.Mechili"
              }
            }
          ]
        }
      }
    }
  ],
  "configuration_version": "1"
}